count_dict_package/__init__.py
count_dict_package/count_dict_module.py
count_dict-1.1.1.dist-info/LICENSE
count_dict-1.1.1.dist-info/METADATA
count_dict-1.1.1.dist-info/WHEEL
count_dict-1.1.1.dist-info/top_level.txt
count_dict-1.1.1.dist-info/RECORD
