Metadata-Version: 2.1
Name: count-dict
Version: 1.1.1
Summary: Count dictionary package in python.
Home-page: https://github.com/fsssosei/count_dict
Author: sosei
Author-email: fss.sosei@gmail.com
License: GNU Affero General Public License v3
Keywords: count,dictionary
Platform: UNKNOWN
Classifier: Development Status :: 5 - Production/Stable
Classifier: License :: OSI Approved :: GNU Affero General Public License v3
Classifier: Programming Language :: Python :: 3.7
Requires-Python: >=3.7
